pysherasync/__init__.py
pysherasync/pysherasync.py
pysherasync-0.2.dist-info/LICENSE
pysherasync-0.2.dist-info/METADATA
pysherasync-0.2.dist-info/WHEEL
pysherasync-0.2.dist-info/top_level.txt
pysherasync-0.2.dist-info/RECORD
